coder_sage/coder.py
coder_sage-1.0.0.dist-info/METADATA
coder_sage-1.0.0.dist-info/WHEEL
coder_sage-1.0.0.dist-info/top_level.txt
coder_sage-1.0.0.dist-info/RECORD
