Metadata-Version: 2.1
Name: coder-sage
Version: 1.0.0
Summary: A testing package of codersage
Author: Shivazi Biswas
